{
	"_version": "1.1.0",
	"resources": [
		{
			"name": ".theming",
			"size": 90,
			"theme": "sap_horizon"
		},
		{
			"name": "Card.less",
			"size": 2677,
			"designtime": true,
			"theme": "sap_horizon"
		},
		{
			"name": "OVPApp.less",
			"size": 1518,
			"designtime": true,
			"theme": "sap_horizon"
		},
		{
			"name": "ObjectStream.less",
			"size": 721,
			"designtime": true,
			"theme": "sap_horizon"
		},
		{
			"name": "css_variables.css",
			"size": 777,
			"theme": "sap_horizon"
		},
		{
			"name": "css_variables.less",
			"size": 94259,
			"designtime": true,
			"theme": "sap_horizon"
		},
		{
			"name": "css_variables.source.less",
			"size": 93897,
			"designtime": true,
			"theme": "sap_horizon"
		},
		{
			"name": "library-RTL.css",
			"size": 55394,
			"theme": "sap_horizon"
		},
		{
			"name": "library-parameters.json",
			"size": 238,
			"theme": "sap_horizon"
		},
		{
			"name": "library.css",
			"size": 55380,
			"theme": "sap_horizon"
		},
		{
			"name": "library.less",
			"size": 5504,
			"designtime": true,
			"theme": "sap_horizon"
		},
		{
			"name": "library.source.less",
			"size": 313,
			"designtime": true,
			"theme": "sap_horizon"
		},
		{
			"name": "library_skeleton-RTL.css",
			"size": 57127,
			"theme": "sap_horizon"
		},
		{
			"name": "library_skeleton.css",
			"size": 57113,
			"theme": "sap_horizon"
		}
	]
}